caltrain_mcp/__init__.py
caltrain_mcp/__main__.py
caltrain_mcp/gtfs.py
caltrain_mcp/py.typed
caltrain_mcp/server.py
caltrain_mcp/data/caltrain-ca-us/agency.txt
caltrain_mcp/data/caltrain-ca-us/calendar.txt
caltrain_mcp/data/caltrain-ca-us/calendar_attributes.txt
caltrain_mcp/data/caltrain-ca-us/calendar_dates.txt
caltrain_mcp/data/caltrain-ca-us/directions.txt
caltrain_mcp/data/caltrain-ca-us/fare_attributes.txt
caltrain_mcp/data/caltrain-ca-us/fare_rider_categories.txt
caltrain_mcp/data/caltrain-ca-us/fare_rules.txt
caltrain_mcp/data/caltrain-ca-us/feed_info.txt
caltrain_mcp/data/caltrain-ca-us/realtime_routes.txt
caltrain_mcp/data/caltrain-ca-us/rider_categories.txt
caltrain_mcp/data/caltrain-ca-us/route_attributes.txt
caltrain_mcp/data/caltrain-ca-us/routes.txt
caltrain_mcp/data/caltrain-ca-us/shapes.txt
caltrain_mcp/data/caltrain-ca-us/stop_attributes.txt
caltrain_mcp/data/caltrain-ca-us/stop_times.txt
caltrain_mcp/data/caltrain-ca-us/stops.txt
caltrain_mcp/data/caltrain-ca-us/transfers.txt
caltrain_mcp/data/caltrain-ca-us/trips.txt
caltrain_mcp-0.8.6.dist-info/METADATA
caltrain_mcp-0.8.6.dist-info/WHEEL
caltrain_mcp-0.8.6.dist-info/entry_points.txt
caltrain_mcp-0.8.6.dist-info/licenses/LICENSE.md
caltrain_mcp-0.8.6.dist-info/RECORD
