Metadata-Version: 2.4
Name: caltrain-mcp
Version: 0.8.6
Summary: Model Context Protocol server for Caltrain schedules
Author-email: David Yen <davidyen1124@gmail.com>
License-File: LICENSE.md
Requires-Python: >=3.13
Requires-Dist: mcp>=1.9.1
Requires-Dist: pandas>=2.2.3
